derm_ita/__init__.py
derm_ita/boarder_removal.py
derm_ita/cropped_center.py
derm_ita/derm_ita.py
derm_ita/ita_core_computations.py
derm_ita/random_patches.py
derm_ita/skin_tone_classification.py
derm_ita/structured_patches.py
tests/__init__.py
tests/test_derm_ita.py
derm_ita-0.0.8.dist-info/LICENSE.txt
derm_ita-0.0.8.dist-info/METADATA
derm_ita-0.0.8.dist-info/WHEEL
derm_ita-0.0.8.dist-info/top_level.txt
derm_ita-0.0.8.dist-info/RECORD
