Metadata-Version: 2.1
Name: derm-ita
Version: 0.0.8
Summary: A package with different strategies to compute individual typology angle
Home-page: https://github.com/acorbin3/derm_ita
Author: Adam Corbin
Author-email: acorbin3@gmail.com
License: UNKNOWN
Platform: UNKNOWN
Classifier: Programming Language :: Python :: 3.9
Classifier: License :: OSI Approved :: MIT License
License-File: LICENSE.txt
Requires-Dist: numpy (>=1.21)
Requires-Dist: Pillow (>=8.4)
Requires-Dist: setuptools (>=57)
Requires-Dist: scikit-image (>=0.19)
Requires-Dist: patchify (>=0.2.3)
Provides-Extra: dev
Requires-Dist: pytest (>=4) ; extra == 'dev'
Requires-Dist: pytest-cov (>=2) ; extra == 'dev'
Provides-Extra: test
Requires-Dist: pytest (>=4) ; extra == 'test'
Requires-Dist: pytest-cov (>=2) ; extra == 'test'
